shipyard_clickup/__init__.py
shipyard_clickup/cli/add_comment.py
shipyard_clickup/cli/create_task.py
shipyard_clickup/cli/edit_task.py
shipyard_clickup/clickup.py
shipyard_clickup-0.1.1.dist-info/METADATA
shipyard_clickup-0.1.1.dist-info/WHEEL
shipyard_clickup-0.1.1.dist-info/RECORD
